tests/__init__.py
tests/video_watermark.py
video_invisible_watermark/__init__.py
video_invisible_watermark/video_watermark.py
video_invisible_watermark-0.1.2.dist-info/METADATA
video_invisible_watermark-0.1.2.dist-info/WHEEL
video_invisible_watermark-0.1.2.dist-info/top_level.txt
video_invisible_watermark-0.1.2.dist-info/RECORD
