Metadata-Version: 2.1
Name: video_invisible_watermark
Version: 0.1.2
Summary: A Python library to embed invisible watermarks into video frames
Home-page: https://github.com/JumiRay/video-invisible-watermark
Author: MingLei Zhou
Author-email: jumiray620@gmail.com
Classifier: Programming Language :: Python :: 3
Classifier: License :: OSI Approved :: MIT License
Classifier: Operating System :: OS Independent
Requires-Python: >=3.6
Requires-Dist: opencv-python
Requires-Dist: scipy
Requires-Dist: Pillow
